Metadata-Version: 2.1
Name: oxfordpy
Version: 1.0.0
Summary: Oxford dictionary python library
Home-page: https://github.com/spacesudo/oxfordpy
Author: Chidera
Author-email: chiderankem2@gmail.com
License: MIT
Keywords: Oxford,dictionary,development
Platform: UNKNOWN
Classifier: Intended Audience :: Developers
Classifier: Topic :: Software Development :: Build Tools
Classifier: License :: OSI Approved :: MIT License
Classifier: Programming Language :: Python :: 3
Classifier: Programming Language :: Python :: 3.7
Classifier: Programming Language :: Python :: 3.8
Classifier: Programming Language :: Python :: 3.9
Classifier: Programming Language :: Python :: 3 :: Only
Requires-Python: >=3.6, <4
